Workbook

Sheet Start Here
B2: Boateng Provisions & Wholesale
B3: Sales, Inventory & Performance Tracker — Demo Template
B5: HOW THIS TEMPLATE WORKS
B7: 1. Sales Tracker tab
B8: Record every sale here — one row per bag, carton or case sold. This is the ONLY tab you type new sales into.
B10: 2. Inventory tab
B11: Track stock in/out per item. Any item below its reorder level turns RED automatically — so you never run out of fast-moving stock like rice, oil or sugar.
B13: 3. Dashboard tab
B14: Everything here updates on its own from the two tabs above. Nothing to edit — just look and decide.
B16: Why this matters
B17: Wholesale shops usually give some customers goods on credit. Separating Cash, MoMo, Bank Transfer and Credit sales shows exactly how much money is truly in hand versus how much is still owed to you.
B20: Tip: duplicate this whole workbook for each new client, then just replace the sample rows with their real data.

Sheet Sales Tracker
A1: DAILY SALES & MOMO TRACKER
A2: Enter one row per sale. Total Revenue and Profit calculate automatically.
A4: Date | B4: Item Name | C4: Category | D4: Quantity Sold | E4: Unit Price (GHS) | F4: Total Revenue (GHS) | G4: Payment Method | H4: Cost of Goods Sold (GHS) | I4: Profit (GHS) | J4: Month
A5: 46143 | B5: Tomato Paste (carton) | C5: Canned Goods | D5: 2 | E5: 340 | F5: =D5*E5 -> 680 | G5: MoMo | H5: 540 | I5: =F5-H5 -> 140 | J5: =TEXT(A5,"mmm yyyy") -> May 2026
A6: 46146 | B6: Flour (50kg bag) | C6: Baking Essentials | D6: 2 | E6: 450 | F6: =D6*E6 -> 900 | G6: Bank Transfer | H6: 760 | I6: =F6-H6 -> 140 | J6: =TEXT(A6,"mmm yyyy") -> May 2026
A7: 46146 | B7: Rice (50kg bag) | C7: Grains & Cereals | D7: 1 | E7: 520 | F7: =D7*E7 -> 520 | G7: MoMo | H7: 440 | I7: =F7-H7 -> 80 | J7: =TEXT(A7,"mmm yyyy") -> May 2026
A8: 46146 | B8: Sugar (50kg bag) | C8: Grains & Cereals | D8: 5 | E8: 480 | F8: =D8*E8 -> 2400 | G8: Cash | H8: 2000 | I8: =F8-H8 -> 400 | J8: =TEXT(A8,"mmm yyyy") -> May 2026
A9: 46147 | B9: Bar Soap (carton) | C9: Household & Toiletries | D9: 3 | E9: 220 | F9: =D9*E9 -> 660 | G9: MoMo | H9: 495 | I9: =F9-H9 -> 165 | J9: =TEXT(A9,"mmm yyyy") -> May 2026
A10: 46147 | B10: Detergent Powder (carton) | C10: Household & Toiletries | D10: 5 | E10: 260 | F10: =D10*E10 -> 1300 | G10: Cash | H10: 1000 | I10: =F10-H10 -> 300 | J10: =TEXT(A10,"mmm yyyy") -> May 2026
A11: 46147 | B11: Flour (50kg bag) | C11: Baking Essentials | D11: 5 | E11: 450 | F11: =D11*E11 -> 2250 | G11: Credit (Owing) | H11: 1900 | I11: =F11-H11 -> 350 | J11: =TEXT(A11,"mmm yyyy") -> May 2026
A12: 46148 | B12: Vegetable Oil (25L gallon) | C12: Cooking Oils | D12: 5 | E12: 620 | F12: =D12*E12 -> 3100 | G12: Cash | H12: 2600 | I12: =F12-H12 -> 500 | J12: =TEXT(A12,"mmm yyyy") -> May 2026
A13: 46149 | B13: Flour (50kg bag) | C13: Baking Essentials | D13: 10 | E13: 450 | F13: =D13*E13 -> 4500 | G13: Cash | H13: 3800 | I13: =F13-H13 -> 700 | J13: =TEXT(A13,"mmm yyyy") -> May 2026
A14: 46151 | B14: Rice (50kg bag) | C14: Grains & Cereals | D14: 5 | E14: 520 | F14: =D14*E14 -> 2600 | G14: Cash | H14: 2200 | I14: =F14-H14 -> 400 | J14: =TEXT(A14,"mmm yyyy") -> May 2026
A15: 46151 | B15: Sardines (carton) | C15: Canned Goods | D15: 5 | E15: 380 | F15: =D15*E15 -> 1900 | G15: Cash | H15: 1500 | I15: =F15-H15 -> 400 | J15: =TEXT(A15,"mmm yyyy") -> May 2026
A16: 46152 | B16: Sugar (50kg bag) | C16: Grains & Cereals | D16: 5 | E16: 480 | F16: =D16*E16 -> 2400 | G16: Cash | H16: 2000 | I16: =F16-H16 -> 400 | J16: =TEXT(A16,"mmm yyyy") -> May 2026
... A83: 46201 | B83: Sardines (carton) | C83: Canned Goods | D83: 2 | E83: 380 | F83: =D83*E83 -> 760 | G83: MoMo | H83: 600 | I83: =F83-H83 -> 160 | J83: =TEXT(A83,"mmm yyyy") -> Jun 2026

Sheet Inventory
A1: INVENTORY ALERT SYSTEM
A2: Rows turn RED automatically when Current Stock drops below Reorder Level.
A4: Item Name | B4: Stock In | C4: Stock Out | D4: Current Stock | E4: Reorder Level | F4: Status
A5: Rice (50kg bag) | B5: 80 | C5: 68 | D5: =B5-C5 -> 12 | E5: 20 | F5: =IF(D5<E5,"Restock Needed","OK") -> Restock Needed
A6: Sugar (50kg bag) | B6: 60 | C6: 52 | D6: =B6-C6 -> 8 | E6: 15 | F6: =IF(D6<E6,"Restock Needed","OK") -> Restock Needed
A7: Vegetable Oil (25L gallon) | B7: 45 | C7: 40 | D7: =B7-C7 -> 5 | E7: 12 | F7: =IF(D7<E7,"Restock Needed","OK") -> Restock Needed
A8: Flour (50kg bag) | B8: 50 | C8: 33 | D8: =B8-C8 -> 17 | E8: 15 | F8: =IF(D8<E8,"Restock Needed","OK") -> OK
A9: Tomato Paste (carton) | B9: 70 | C9: 63 | D9: =B9-C9 -> 7 | E9: 20 | F9: =IF(D9<E9,"Restock Needed","OK") -> Restock Needed
A10: Sardines (carton) | B10: 55 | C10: 49 | D10: =B10-C10 -> 6 | E10: 15 | F10: =IF(D10<E10,"Restock Needed","OK") -> Restock Needed
A11: Evaporated Milk (carton) | B11: 65 | C11: 56 | D11: =B11-C11 -> 9 | E11: 18 | F11: =IF(D11<E11,"Restock Needed","OK") -> Restock Needed
A12: Detergent Powder (carton) | B12: 40 | C12: 36 | D12: =B12-C12 -> 4 | E12: 12 | F12: =IF(D12<E12,"Restock Needed","OK") -> Restock Needed
A13: Bar Soap (carton) | B13: 45 | C13: 30 | D13: =B13-C13 -> 15 | E13: 12 | F13: =IF(D13<E13,"Restock Needed","OK") -> OK
A14: Salt (50kg bag) | B14: 35 | C14: 22 | D14: =B14-C14 -> 13 | E14: 10 | F14: =IF(D14<E14,"Restock Needed","OK") -> OK

Sheet Dashboard
A1: BOATENG PROVISIONS & WHOLESALE — PERFORMANCE DASHBOARD
A2: Updates automatically from Sales Tracker and Inventory tabs.
A4: TOTAL REVENUE | D4: TOTAL PROFIT | G4: TOTAL COGS | J4: PROFIT MARGIN
A5: =SUM('Sales Tracker'!F5:F83) -> 118890 | D5: =SUM('Sales Tracker'!I5:I83) -> 22385 | G5: =SUM('Sales Tracker'!H5:H83) -> 96505 | J5: =D5/A5 -> 0.18828329
A9: MONTHLY REVENUE VS PROFIT | E9: TOP 5 BEST-SELLING ITEMS (BY QTY) | I9: helper (qty by item)
A10: Month | B10: Revenue (GHS) | C10: Profit (GHS) | E10: Item Name | F10: Qty Sold | G10: Revenue (GHS) | I10: Rice (50kg bag) | J10: =SUMIF('Sales Tracker'!$B$5:$B$83,I10,'Sales Tracker'!$D$5:$D$83) -> 50
A11: May 2026 | B11: =SUMIF('Sales Tracker'!$J$5:$J$83,A11,'Sales Tracker'!$F$5:$F$83) -> 71470 | C11: =SUMIF('Sales Tracker'!$J$5:$J$83,A11,'Sales Tracker'!$I$5:$I$83) -> 13340 | E11: =INDEX($I$10:$I$19,MATCH(F11,$J$10:$J$19,0)) -> Bar Soap (carton) | F11: =LARGE($J$10:$J$19,1) -> 51 | G11: =SUMIF('Sales Tracker'!$B$5:$B$83,E11,'Sales Tracker'!$F$5:$F$83) -> 11220 | I11: Sugar (50kg bag) | J11: =SUMIF('Sales Tracker'!$B$5:$B$83,I11,'Sales Tracker'!$D$5:$D$83) -> 27
A12: Jun 2026 | B12: =SUMIF('Sales Tracker'!$J$5:$J$83,A12,'Sales Tracker'!$F$5:$F$83) -> 47420 | C12: =SUMIF('Sales Tracker'!$J$5:$J$83,A12,'Sales Tracker'!$I$5:$I$83) -> 9045 | E12: =INDEX($I$10:$I$19,MATCH(F12,$J$10:$J$19,0)) -> Rice (50kg bag) | F12: =LARGE($J$10:$J$19,2) -> 50 | G12: =SUMIF('Sales Tracker'!$B$5:$B$83,E12,'Sales Tracker'!$F$5:$F$83) -> 26000 | I12: Vegetable Oil (25L gallon) | J12: =SUMIF('Sales Tracker'!$B$5:$B$83,I12,'Sales Tracker'!$D$5:$D$83) -> 17
E13: =INDEX($I$10:$I$19,MATCH(F13,$J$10:$J$19,0)) -> Detergent Powder (carton) | F13: =LARGE($J$10:$J$19,3) -> 42 | G13: =SUMIF('Sales Tracker'!$B$5:$B$83,E13,'Sales Tracker'!$F$5:$F$83) -> 10920 | I13: Flour (50kg bag) | J13: =SUMIF('Sales Tracker'!$B$5:$B$83,I13,'Sales Tracker'!$D$5:$D$83) -> 38
E14: =INDEX($I$10:$I$19,MATCH(F14,$J$10:$J$19,0)) -> Flour (50kg bag) | F14: =LARGE($J$10:$J$19,4) -> 38 | G14: =SUMIF('Sales Tracker'!$B$5:$B$83,E14,'Sales Tracker'!$F$5:$F$83) -> 17100 | I14: Tomato Paste (carton) | J14: =SUMIF('Sales Tracker'!$B$5:$B$83,I14,'Sales Tracker'!$D$5:$D$83) -> 22
E15: =INDEX($I$10:$I$19,MATCH(F15,$J$10:$J$19,0)) -> Sardines (carton) | F15: =LARGE($J$10:$J$19,5) -> 34 | G15: =SUMIF('Sales Tracker'!$B$5:$B$83,E15,'Sales Tracker'!$F$5:$F$83) -> 12920 | I15: Sardines (carton) | J15: =SUMIF('Sales Tracker'!$B$5:$B$83,I15,'Sales Tracker'!$D$5:$D$83) -> 34
I16: Evaporated Milk (carton) | J16: =SUMIF('Sales Tracker'!$B$5:$B$83,I16,'Sales Tracker'!$D$5:$D$83) -> 16
I17: Detergent Powder (carton) | J17: =SUMIF('Sales Tracker'!$B$5:$B$83,I17,'Sales Tracker'!$D$5:$D$83) -> 42
A18: PAYMENT METHOD SPLIT | E18: ITEMS NEEDING RESTOCK | I18: Bar Soap (carton) | J18: =SUMIF('Sales Tracker'!$B$5:$B$83,I18,'Sales Tracker'!$D$5:$D$83) -> 51
A19: Payment Method | B19: Total Revenue (GHS) | E19: Item Name | F19: Current Stock | G19: Reorder Level | I19: Salt (50kg bag) | J19: =SUMIF('Sales Tracker'!$B$5:$B$83,I19,'Sales Tracker'!$D$5:$D$83) -> 33
A20: Cash | B20: =SUMIF('Sales Tracker'!$G$5:$G$83,A20,'Sales Tracker'!$F$5:$F$83) -> 50720 | E20: =IF(Inventory!F5="Restock Needed",Inventory!A5,"") -> Rice (50kg bag) | F20: =IF(Inventory!F5="Restock Needed",Inventory!D5,"") -> 12 | G20: =IF(Inventory!F5="Restock Needed",Inventory!E5,"") -> 20
A21: MoMo | B21: =SUMIF('Sales Tracker'!$G$5:$G$83,A21,'Sales Tracker'!$F$5:$F$83) -> 37860 | E21: =IF(Inventory!F6="Restock Needed",Inventory!A6,"") -> Sugar (50kg bag) | F21: =IF(Inventory!F6="Restock Needed",Inventory!D6,"") -> 8 | G21: =IF(Inventory!F6="Restock Needed",Inventory!E6,"") -> 15
A22: Bank Transfer | B22: =SUMIF('Sales Tracker'!$G$5:$G$83,A22,'Sales Tracker'!$F$5:$F$83) -> 13880 | E22: =IF(Inventory!F7="Restock Needed",Inventory!A7,"") -> Vegetable Oil (25L gallon) | F22: =IF(Inventory!F7="Restock Needed",Inventory!D7,"") -> 5 | G22: =IF(Inventory!F7="Restock Needed",Inventory!E7,"") -> 12
A23: Credit (Owing) | B23: =SUMIF('Sales Tracker'!$G$5:$G$83,A23,'Sales Tracker'!$F$5:$F$83) -> 16430 | E23: =IF(Inventory!F8="Restock Needed",Inventory!A8,"") | F23: =IF(Inventory!F8="Restock Needed",Inventory!D8,"") | G23: =IF(Inventory!F8="Restock Needed",Inventory!E8,"")
E24: =IF(Inventory!F9="Restock Needed",Inventory!A9,"") -> Tomato Paste (carton) | F24: =IF(Inventory!F9="Restock Needed",Inventory!D9,"") -> 7 | G24: =IF(Inventory!F9="Restock Needed",Inventory!E9,"") -> 20
E25: =IF(Inventory!F10="Restock Needed",Inventory!A10,"") -> Sardines (carton) | F25: =IF(Inventory!F10="Restock Needed",Inventory!D10,"") -> 6 | G25: =IF(Inventory!F10="Restock Needed",Inventory!E10,"") -> 15
E26: =IF(Inventory!F11="Restock Needed",Inventory!A11,"") -> Evaporated Milk (carton) | F26: =IF(Inventory!F11="Restock Needed",Inventory!D11,"") -> 9 | G26: =IF(Inventory!F11="Restock Needed",Inventory!E11,"") -> 18
E27: =IF(Inventory!F12="Restock Needed",Inventory!A12,"") -> Detergent Powder (carton) | F27: =IF(Inventory!F12="Restock Needed",Inventory!D12,"") -> 4 | G27: =IF(Inventory!F12="Restock Needed",Inventory!E12,"") -> 12
E28: =IF(Inventory!F13="Restock Needed",Inventory!A13,"") | F28: =IF(Inventory!F13="Restock Needed",Inventory!D13,"") | G28: =IF(Inventory!F13="Restock Needed",Inventory!E13,"")
E29: =IF(Inventory!F14="Restock Needed",Inventory!A14,"") | F29: =IF(Inventory!F14="Restock Needed",Inventory!D14,"") | G29: =IF(Inventory!F14="Restock Needed",Inventory!E14,"")
